{"errors":[],"warnings":[],"version":"1.15.0","hash":"0bd979d41c0ae68e3998","publicPath":"/","assetsByChunkName":{"manifest":"static/crmplus/js/manifest.29ba8724e08d3d375150.js","vendor":"static/crmplus/js/vendor.e6b1dbe25264a926c2c8.js","main":["static/crmplus/js/main.84201e05b55745203de8.js","static/crmplus/css/main.c6e8ddcc8d8ddcee443b5132adfd0b58.css"]},"assets":[{"name":"static/crmplus/js/manifest.29ba8724e08d3d375150.js","size":827,"chunks":[0],"chunkNames":["manifest"]},{"name":"static/crmplus/js/vendor.e6b1dbe25264a926c2c8.js","size":314899,"chunks":[1,0],"chunkNames":["vendor"]},{"name":"static/crmplus/js/main.84201e05b55745203de8.js","size":7767,"chunks":[2,0],"chunkNames":["main"]},{"name":"static/crmplus/css/main.c6e8ddcc8d8ddcee443b5132adfd0b58.css","size":41,"chunks":[2,0],"chunkNames":["main"]},{"name":"index.html","size":665,"chunks":[],"chunkNames":[],"emitted":true},{"name":"webpack.stats.json","size":0,"chunks":[],"chunkNames":[]}],"chunks":[{"id":0,"rendered":true,"initial":true,"entry":true,"extraAsync":false,"size":0,"names":["manifest"],"files":["static/crmplus/js/manifest.29ba8724e08d3d375150.js"],"hash":"29ba8724e08d3d375150","parents":[],"origins":[]},{"id":1,"rendered":true,"initial":true,"entry":false,"extraAsync":false,"size":1137774,"names":["vendor"],"files":["static/crmplus/js/vendor.e6b1dbe25264a926c2c8.js"],"hash":"e6b1dbe25264a926c2c8","parents":[0],"origins":[]},{"id":2,"rendered":true,"initial":true,"entry":false,"extraAsync":false,"size":15592,"names":["main"],"files":["static/crmplus/js/main.84201e05b55745203de8.js","static/crmplus/css/main.c6e8ddcc8d8ddcee443b5132adfd0b58.css"],"hash":"84201e05b55745203de8","parents":[1],"origins":[{"moduleId":0,"module":"multi main","moduleIdentifier":"multi main","moduleName":"multi main","loc":"","name":"main","reasons":[]}]}],"children":[{"errors":[],"warnings":[],"publicPath":"/","assetsByChunkName":{},"assets":[{"name":"index.html","size":558480,"chunks":[0],"chunkNames":[]}],"chunks":[{"id":0,"rendered":true,"initial":true,"entry":true,"extraAsync":false,"size":540557,"names":[],"files":["index.html"],"hash":"b52323425df5acc58744","parents":[],"origins":[{"moduleId":0,"module":"/Users/jacky/study/ajax1024/node_modules/html-webpack-plugin/lib/loader.js!/Users/jacky/study/ajax1024/index.html","moduleIdentifier":"/Users/jacky/study/ajax1024/node_modules/html-webpack-plugin/lib/loader.js!/Users/jacky/study/ajax1024/index.html","moduleName":"./~/html-webpack-plugin/lib/loader.js!./index.html","loc":"","reasons":[]}]}],"children":[],"name":"html-webpack-plugin for \"index.html\""},{"errors":[],"warnings":[],"publicPath":"/","assetsByChunkName":{},"assets":[],"chunks":[{"id":0,"rendered":true,"initial":true,"entry":true,"extraAsync":false,"size":1707,"names":[],"files":["extract-text-webpack-plugin-output-filename"],"hash":"a449f7cc6b2a3a90e339","parents":[],"origins":[{"moduleId":0,"module":"/Users/jacky/study/ajax1024/node_modules/css-loader/index.js!/Users/jacky/study/ajax1024/node_modules/less-loader/index.js!/Users/jacky/study/ajax1024/node_modules/postcss-loader/index.js!/Users/jacky/study/ajax1024/src/components/home/home.less","moduleIdentifier":"/Users/jacky/study/ajax1024/node_modules/css-loader/index.js!/Users/jacky/study/ajax1024/node_modules/less-loader/index.js!/Users/jacky/study/ajax1024/node_modules/postcss-loader/index.js!/Users/jacky/study/ajax1024/src/components/home/home.less","moduleName":"./~/css-loader!./~/less-loader!./~/postcss-loader!./src/components/home/home.less","loc":"","reasons":[]}]}],"children":[],"name":"extract-text-webpack-plugin"}]}